<annotation>
	<folder>images</folder>
	<filename>000016.jpg</filename>
	<path>/Users/kevin.nguyen/Projects/darkflow/train/images/000016.jpg</path>
	<source>
		<database>Unknown</database>
	</source>
	<size>
		<width>590</width>
		<height>649</height>
		<depth>3</depth>
	</size>
	<segmented>0</segmented>
	<object>
		<name>arrow</name>
		<pose>Unspecified</pose>
		<truncated>0</truncated>
		<difficult>0</difficult>
		<bndbox>
			<xmin>69</xmin>
			<ymin>74</ymin>
			<xmax>191</xmax>
			<ymax>173</ymax>
		</bndbox>
	</object>
	<object>
		<name>arrow</name>
		<pose>Unspecified</pose>
		<truncated>0</truncated>
		<difficult>0</difficult>
		<bndbox>
			<xmin>220</xmin>
			<ymin>68</ymin>
			<xmax>388</xmax>
			<ymax>148</ymax>
		</bndbox>
	</object>
	<object>
		<name>arrow</name>
		<pose>Unspecified</pose>
		<truncated>0</truncated>
		<difficult>0</difficult>
		<bndbox>
			<xmin>411</xmin>
			<ymin>61</ymin>
			<xmax>560</xmax>
			<ymax>165</ymax>
		</bndbox>
	</object>
	<object>
		<name>arrow</name>
		<pose>Unspecified</pose>
		<truncated>0</truncated>
		<difficult>0</difficult>
		<bndbox>
			<xmin>51</xmin>
			<ymin>201</ymin>
			<xmax>211</xmax>
			<ymax>318</ymax>
		</bndbox>
	</object>
	<object>
		<name>arrow</name>
		<pose>Unspecified</pose>
		<truncated>0</truncated>
		<difficult>0</difficult>
		<bndbox>
			<xmin>405</xmin>
			<ymin>181</ymin>
			<xmax>558</xmax>
			<ymax>295</ymax>
		</bndbox>
	</object>
	<object>
		<name>arrow</name>
		<pose>Unspecified</pose>
		<truncated>0</truncated>
		<difficult>0</difficult>
		<bndbox>
			<xmin>46</xmin>
			<ymin>348</ymin>
			<xmax>179</xmax>
			<ymax>397</ymax>
		</bndbox>
	</object>
	<object>
		<name>arrow</name>
		<pose>Unspecified</pose>
		<truncated>0</truncated>
		<difficult>0</difficult>
		<bndbox>
			<xmin>195</xmin>
			<ymin>292</ymin>
			<xmax>403</xmax>
			<ymax>410</ymax>
		</bndbox>
	</object>
	<object>
		<name>arrow</name>
		<pose>Unspecified</pose>
		<truncated>0</truncated>
		<difficult>0</difficult>
		<bndbox>
			<xmin>436</xmin>
			<ymin>321</ymin>
			<xmax>539</xmax>
			<ymax>417</ymax>
		</bndbox>
	</object>
	<object>
		<name>arrow</name>
		<pose>Unspecified</pose>
		<truncated>0</truncated>
		<difficult>0</difficult>
		<bndbox>
			<xmin>14</xmin>
			<ymin>430</ymin>
			<xmax>219</xmax>
			<ymax>605</ymax>
		</bndbox>
	</object>
	<object>
		<name>arrow</name>
		<pose>Unspecified</pose>
		<truncated>0</truncated>
		<difficult>0</difficult>
		<bndbox>
			<xmin>243</xmin>
			<ymin>424</ymin>
			<xmax>389</xmax>
			<ymax>613</ymax>
		</bndbox>
	</object>
	<object>
		<name>arrow</name>
		<pose>Unspecified</pose>
		<truncated>0</truncated>
		<difficult>0</difficult>
		<bndbox>
			<xmin>395</xmin>
			<ymin>432</ymin>
			<xmax>540</xmax>
			<ymax>604</ymax>
		</bndbox>
	</object>
</annotation>
